uc_pidfile/__init__.py
uc_pidfile-0.0.3.dist-info/LICENSE
uc_pidfile-0.0.3.dist-info/METADATA
uc_pidfile-0.0.3.dist-info/WHEEL
uc_pidfile-0.0.3.dist-info/top_level.txt
uc_pidfile-0.0.3.dist-info/RECORD
