Metadata-Version: 2.1
Name: uc-pidfile
Version: 0.0.3
Summary: A set of classes and functions for managing pidfile.
Home-page: https://github.com/dentist128/uc_pidfile
Author: Eduard S. Markelov
Author-email: markeloveduard@gmail.com
License: UNKNOWN
Platform: UNKNOWN
Classifier: Programming Language :: Python :: 3
Classifier: License :: OSI Approved :: GNU Affero General Public License v3
Classifier: Operating System :: OS Independent
Requires-Python: >=3.4, <4
